sentimental_onix/__init__.py
sentimental_onix/__main__.py
sentimental_onix/pipeline.py
sentimental_onix/util.py
sentimental_onix/inference/__init__.py
sentimental_onix/inference/en/__init__.py
sentimental_onix-0.0.2.dist-info/LICENSE
sentimental_onix-0.0.2.dist-info/METADATA
sentimental_onix-0.0.2.dist-info/WHEEL
sentimental_onix-0.0.2.dist-info/top_level.txt
sentimental_onix-0.0.2.dist-info/RECORD
