Metadata-Version: 2.1
Name: sentimental-onix
Version: 0.0.2
Summary: spacy pipeline component for sentiment analysis using onnx
Author-email: sloev <johannes.valbjorn@gmail.com>
License: MIT License
Project-URL: Homepage, https://github.com/sloev/sentimental-onix
Keywords: spacy,onnx,sentiment,english,nlp
Classifier: Development Status :: 6 - Mature
Classifier: Intended Audience :: Developers
Classifier: Natural Language :: English
Classifier: Programming Language :: Python :: 3.8
Classifier: Programming Language :: Python :: 3.9
Classifier: Programming Language :: Python :: 3.10
Requires-Python: >=3.8
License-File: LICENSE
Requires-Dist: spacy (>=3.0.3)
Requires-Dist: onnx (>=1.13.1)
Requires-Dist: onnxruntime (>=1.14.1)
Requires-Dist: numpy
Provides-Extra: dev
Requires-Dist: black (>=23.1.0) ; extra == 'dev'
Requires-Dist: pytest ; extra == 'dev'
